cyz/__init__.py
cyz/mail.py
cyz-0.0.5.dist-info/METADATA
cyz-0.0.5.dist-info/WHEEL
cyz-0.0.5.dist-info/top_level.txt
cyz-0.0.5.dist-info/RECORD
